basitcrypto/__init__.py
basitcrypto/crypto.py
basitcrypto-0.2.0.dist-info/licenses/LICENSE
basitcrypto-0.2.0.dist-info/METADATA
basitcrypto-0.2.0.dist-info/WHEEL
basitcrypto-0.2.0.dist-info/top_level.txt
basitcrypto-0.2.0.dist-info/RECORD
