Metadata-Version: 2.4
Name: basitcrypto
Version: 0.2.0
Summary: Simple encryption library (XOR, Caesar)
Home-page: https://github.com/yourusername/basitcrypto
Author: Al-Junaid
Author-email: Al-Junaid@google.com
Classifier: Programming Language :: Python :: 3
Classifier: License :: OSI Approved :: MIT License
Requires-Python: >=3.7
License-File: LICENSE
Dynamic: author
Dynamic: author-email
Dynamic: classifier
Dynamic: description
Dynamic: description-content-type
Dynamic: home-page
Dynamic: license-file
Dynamic: requires-python
Dynamic: summary
